django_code_generator/__init__.py
django_code_generator/exceptions.py
django_code_generator/models.py
django_code_generator/renders.py
django_code_generator/templates.py
django_code_generator/management/__init__.py
django_code_generator/management/commands/__init__.py
django_code_generator/management/commands/generator.py
django_code_generator/templates/admin/admin/__init__.py
django_code_generator/templates/api/api/__init__.py
django_code_generator/templates/api/api/serializers.py
django_code_generator/templates/api/api/viewsets.py
django_code_generator/templatetags/__init__.py
django_code_generator/templatetags/code_generator_tags.py
django_code_generator/tests/__init__.py
django_code_generator/tests/test_django_code_generator.py
django_code_generator-0.2.2.dist-info/AUTHORS.rst
django_code_generator-0.2.2.dist-info/LICENSE
django_code_generator-0.2.2.dist-info/METADATA
django_code_generator-0.2.2.dist-info/WHEEL
django_code_generator-0.2.2.dist-info/top_level.txt
django_code_generator-0.2.2.dist-info/RECORD
