Metadata-Version: 2.1
Name: django-code-generator
Version: 0.2.2
Summary: Generate code from Django models for faster development
Home-page: https://github.com/Nekmo/django-code-generator/
Author: Nekmo
Author-email: contacto@nekmo.com
License: UNKNOWN
Download-URL: https://github.com/Nekmo/django-code-generator/archive/master.zip
Keywords: django-code-generator
Platform: linux
Classifier: License :: OSI Approved :: MIT License
Classifier: Programming Language :: Python :: 3.7
Classifier: Programming Language :: Python :: 3 :: Only
Classifier: Programming Language :: Python :: 3.8
Classifier: Programming Language :: Python :: 3.5
Classifier: Programming Language :: Python :: 3.6
Classifier: Operating System :: POSIX
Classifier: Operating System :: POSIX :: Linux
Classifier: Natural Language :: English
Classifier: Development Status :: 5 - Production/Stable
Provides: django_code_generator
Requires-Dist: Django
